stockmarket/__init__.py
stockmarket-0.0.1.dist-info/LICENSE
stockmarket-0.0.1.dist-info/WHEEL
stockmarket-0.0.1.dist-info/METADATA
stockmarket-0.0.1.dist-info/RECORD
